rjango/__init__.py
rjango/devtools/__init__.py
rjango/devtools/tests/__init__.py
rjango/devtools/tests/factory.py
rjango.devtools-0.1.10.dist-info/METADATA
rjango.devtools-0.1.10.dist-info/WHEEL
rjango.devtools-0.1.10.dist-info/top_level.txt
rjango.devtools-0.1.10.dist-info/RECORD
