Metadata-Version: 2.1
Name: rjango.devtools
Version: 0.1.10
Summary: Tools and utilities to easy devtools API development with Rjango
Home-page: UNKNOWN
Author: Nicholas Romero
Author-email: ncrmro@gmail.com
License: MIT License
Platform: UNKNOWN
Requires-Dist: coverage (>=4.5.3)
Requires-Dist: django-cors-headers (>=2.5.3)
Requires-Dist: factory-boy (>=2.5.3)
Requires-Dist: pre-commit (>=1.15.2)
